active_wrapper/__init__.py
active_wrapper/commands/__init__.py
active_wrapper/commands/application.py
active_wrapper/commands/command.py
active_wrapper/commands/migrations/__init__.py
active_wrapper/commands/migrations/base_command.py
active_wrapper/commands/migrations/install_command.py
active_wrapper/commands/migrations/make_command.py
active_wrapper/commands/migrations/migrate_command.py
active_wrapper/commands/migrations/refresh_command.py
active_wrapper/commands/migrations/reset_command.py
active_wrapper/commands/migrations/rollback_command.py
active_wrapper/commands/migrations/status_command.py
active_wrapper/commands/models/__init__.py
active_wrapper/commands/models/make_command.py
active_wrapper/commands/models/stubs.py
active_wrapper/commands/seeds/__init__.py
active_wrapper/commands/seeds/base_command.py
active_wrapper/commands/seeds/make_command.py
active_wrapper/commands/seeds/seed_command.py
active_wrapper/connections/__init__.py
active_wrapper/connections/connection.py
active_wrapper/connections/connection_interface.py
active_wrapper/connections/connection_resolver_interface.py
active_wrapper/connections/mysql_connection.py
active_wrapper/connections/postgres_connection.py
active_wrapper/connections/sqlite_connection.py
active_wrapper/connectors/__init__.py
active_wrapper/connectors/connection_factory.py
active_wrapper/connectors/connector.py
active_wrapper/connectors/mysql_connector.py
active_wrapper/connectors/postgres_connector.py
active_wrapper/connectors/sqlite_connector.py
active_wrapper/database_manager.py
active_wrapper/dbal/__init__.py
active_wrapper/dbal/abstract_asset.py
active_wrapper/dbal/column.py
active_wrapper/dbal/column_diff.py
active_wrapper/dbal/comparator.py
active_wrapper/dbal/exceptions/__init__.py
active_wrapper/dbal/foreign_key_constraint.py
active_wrapper/dbal/identifier.py
active_wrapper/dbal/index.py
active_wrapper/dbal/mysql_schema_manager.py
active_wrapper/dbal/platforms/__init__.py
active_wrapper-0.1.4.dist-info/LICENSE
active_wrapper-0.1.4.dist-info/METADATA
active_wrapper-0.1.4.dist-info/WHEEL
active_wrapper-0.1.4.dist-info/RECORD
